dss_projectfutura/__init__.py
dss_projectfutura/cli.py
dss_projectfutura/model.py
dss_projectfutura/text.py
dss_projectfutura/tokenizer.py
dss_projectfutura-0.2.4.dist-info/LICENSE
dss_projectfutura-0.2.4.dist-info/METADATA
dss_projectfutura-0.2.4.dist-info/WHEEL
dss_projectfutura-0.2.4.dist-info/top_level.txt
dss_projectfutura-0.2.4.dist-info/RECORD
