Metadata-Version: 2.1
Name: dss-projectfutura
Version: 0.2.4
Summary: Content Generation based on Caches
Author-email: Jan Garcia <jancraft888@jdevstudios.es>, Saula Sanz <sourcepaint@jdevstudios.es>
Project-URL: Homepage, https://gitlab.com/project-futura/dss
Project-URL: Bug Tracker, https://gitlab.com/project-futura/dss/-/issues
Classifier: Programming Language :: Python :: 3
Classifier: License :: OSI Approved :: MIT License
Classifier: Operating System :: OS Independent
Requires-Python: >=3.7
License-File: LICENSE
